[{"id": 7,"sim_time": 3701284.986877,"stable": 1,"cost": 74.300000,"upper_node": 841,"sim_proc": 1,"sim_proc_multi": 1000,"preemption": 0,"scheduler": "FIFO","time_slice": 0.040000,"type": "node","parameters": {"telemetry": {"service_demand": 0.040014,"response_time": 0.040982,"utilization_factor": 0.026420,"number_mean_queue": 0.027059,"lambda_in": 0.660262},"transition": {"service_demand": 0.000000,"response_time": 0.000000,"utilization_factor": 0.000000,"number_mean_queue": 0.000000,"lambda_in": 0.000000},"command": {"service_demand": 0.000000,"response_time": 0.000000,"utilization_factor": 0.000000,"number_mean_queue": 0.000000,"lambda_in": 0.000000},"batch": {"service_demand": 0.000000,"response_time": 0.000000,"utilization_factor": 0.000000,"number_mean_queue": 0.000000,"lambda_in": 0.000000},"N_new": 0.027069,"N_new_stable": 0.027059},"node_type": "regional"},{"id": 101,"sim_time": 3701281.206515,"stable": 1,"cost": 92.300000,"upper_node": 848,"sim_proc": 1,"sim_proc_multi": 1000,"preemption": 0,"scheduler": "FIFO","time_slice": 0.200000,"type": "node","parameters": {"telemetry": {"service_demand": 0.199903,"response_time": 0.214011,"utilization_factor": 0.065962,"number_mean_queue": 0.070618,"lambda_in": 0.329972},"transition": {"service_demand": 0.000000,"response_time": 0.000000,"utilization_factor": 0.000000,"number_mean_queue": 0.000000,"lambda_in": 0.000000},"command": {"service_demand": 0.000000,"response_time": 0.000000,"utilization_factor": 0.000000,"number_mean_queue": 0.000000,"lambda_in": 0.000000},"batch": {"service_demand": 0.000000,"response_time": 0.000000,"utilization_factor": 0.000000,"number_mean_queue": 0.000000,"lambda_in": 0.000000},"N_new": 0.070643,"N_new_stable": 0.070618},"node_type": "local"},{"id": 102,"sim_time": 3701289.218773,"stable": 1,"cost": 92.300000,"upper_node": 848,"sim_proc": 1,"sim_proc_multi": 1000,"preemption": 0,"scheduler": "FIFO","time_slice": 0.200000,"type": "node","parameters": {"telemetry": {"service_demand": 0.200220,"response_time": 0.214448,"utilization_factor": 0.066019,"number_mean_queue": 0.070711,"lambda_in": 0.329733},"transition": {"service_demand": 0.000000,"response_time": 0.000000,"utilization_factor": 0.000000,"number_mean_queue": 0.000000,"lambda_in": 0.000000},"command": {"service_demand": 0.000000,"response_time": 0.000000,"utilization_factor": 0.000000,"number_mean_queue": 0.000000,"lambda_in": 0.000000},"batch": {"service_demand": 0.000000,"response_time": 0.000000,"utilization_factor": 0.000000,"number_mean_queue": 0.000000,"lambda_in": 0.000000},"N_new": 0.070734,"N_new_stable": 0.070711},"node_type": "local"},{"id": 103,"sim_time": 3701287.880460,"stable": 1,"cost": 92.300000,"upper_node": 848,"sim_proc": 1,"sim_proc_multi": 1000,"preemption": 0,"scheduler": "FIFO","time_slice": 0.200000,"type": "node","parameters": {"telemetry": {"service_demand": 0.199980,"response_time": 0.214154,"utilization_factor": 0.066026,"number_mean_queue": 0.070706,"lambda_in": 0.330165},"transition": {"service_demand": 0.000000,"response_time": 0.000000,"utilization_factor": 0.000000,"number_mean_queue": 0.000000,"lambda_in": 0.000000},"command": {"service_demand": 0.000000,"response_time": 0.000000,"utilization_factor": 0.000000,"number_mean_queue": 0.000000,"lambda_in": 0.000000},"batch": {"service_demand": 0.000000,"response_time": 0.000000,"utilization_factor": 0.000000,"number_mean_queue": 0.000000,"lambda_in": 0.000000},"N_new": 0.070732,"N_new_stable": 0.070706},"node_type": "local"},{"id": 104,"sim_time": 3701287.619267,"stable": 1,"cost": 92.300000,"upper_node": 848,"sim_proc": 1,"sim_proc_multi": 1000,"preemption": 0,"scheduler": "FIFO","time_slice": 0.200000,"type": "node","parameters": {"telemetry": {"service_demand": 0.200045,"response_time": 0.214367,"utilization_factor": 0.066139,"number_mean_queue": 0.070875,"lambda_in": 0.330622},"transition": {"service_demand": 0.000000,"response_time": 0.000000,"utilization_factor": 0.000000,"number_mean_queue": 0.000000,"lambda_in": 0.000000},"command": {"service_demand": 0.000000,"response_time": 0.000000,"utilization_factor": 0.000000,"number_mean_queue": 0.000000,"lambda_in": 0.000000},"batch": {"service_demand": 0.000000,"response_time": 0.000000,"utilization_factor": 0.000000,"number_mean_queue": 0.000000,"lambda_in": 0.000000},"N_new": 0.070894,"N_new_stable": 0.070875},"node_type": "local"},{"id": 105,"sim_time": 3701286.158508,"stable": 1,"cost": 92.300000,"upper_node": 848,"sim_proc": 1,"sim_proc_multi": 1000,"preemption": 0,"scheduler": "FIFO","time_slice": 0.200000,"type": "node","parameters": {"telemetry": {"service_demand": 0.199848,"response_time": 0.213926,"utilization_factor": 0.066061,"number_mean_queue": 0.070714,"lambda_in": 0.330555},"transition": {"service_demand": 0.000000,"response_time": 0.000000,"utilization_factor": 0.000000,"number_mean_queue": 0.000000,"lambda_in": 0.000000},"command": {"service_demand": 0.000000,"response_time": 0.000000,"utilization_factor": 0.000000,"number_mean_queue": 0.000000,"lambda_in": 0.000000},"batch": {"service_demand": 0.000000,"response_time": 0.000000,"utilization_factor": 0.000000,"number_mean_queue": 0.000000,"lambda_in": 0.000000},"N_new": 0.070739,"N_new_stable": 0.070714},"node_type": "local"},{"id": 106,"sim_time": 3701287.584181,"stable": 1,"cost": 92.300000,"upper_node": 848,"sim_proc": 1,"sim_proc_multi": 1000,"preemption": 0,"scheduler": "FIFO","time_slice": 0.200000,"type": "node","parameters": {"telemetry": {"service_demand": 0.200256,"response_time": 0.214313,"utilization_factor": 0.066086,"number_mean_queue": 0.070725,"lambda_in": 0.330009},"transition": {"service_demand": 0.000000,"response_time": 0.000000,"utilization_factor": 0.000000,"number_mean_queue": 0.000000,"lambda_in": 0.000000},"command": {"service_demand": 0.000000,"response_time": 0.000000,"utilization_factor": 0.000000,"number_mean_queue": 0.000000,"lambda_in": 0.000000},"batch": {"service_demand": 0.000000,"response_time": 0.000000,"utilization_factor": 0.000000,"number_mean_queue": 0.000000,"lambda_in": 0.000000},"N_new": 0.070750,"N_new_stable": 0.070725},"node_type": "local"},{"id": 107,"sim_time": 3701288.123794,"stable": 1,"cost": 92.300000,"upper_node": 848,"sim_proc": 1,"sim_proc_multi": 1000,"preemption": 0,"scheduler": "FIFO","time_slice": 0.200000,"type": "node","parameters": {"telemetry": {"service_demand": 0.199977,"response_time": 0.214007,"utilization_factor": 0.065986,"number_mean_queue": 0.070615,"lambda_in": 0.329965},"transition": {"service_demand": 0.000000,"response_time": 0.000000,"utilization_factor": 0.000000,"number_mean_queue": 0.000000,"lambda_in": 0.000000},"command": {"service_demand": 0.000000,"response_time": 0.000000,"utilization_factor": 0.000000,"number_mean_queue": 0.000000,"lambda_in": 0.000000},"batch": {"service_demand": 0.000000,"response_time": 0.000000,"utilization_factor": 0.000000,"number_mean_queue": 0.000000,"lambda_in": 0.000000},"N_new": 0.070641,"N_new_stable": 0.070615},"node_type": "local"},{"id": 108,"sim_time": 3701289.944737,"stable": 1,"cost": 92.300000,"upper_node": 848,"sim_proc": 1,"sim_proc_multi": 1000,"preemption": 0,"scheduler": "FIFO","time_slice": 0.200000,"type": "node","parameters": {"telemetry": {"service_demand": 0.200021,"response_time": 0.214102,"utilization_factor": 0.065987,"number_mean_queue": 0.070633,"lambda_in": 0.329902},"transition": {"service_demand": 0.000000,"response_time": 0.000000,"utilization_factor": 0.000000,"number_mean_queue": 0.000000,"lambda_in": 0.000000},"command": {"service_demand": 0.000000,"response_time": 0.000000,"utilization_factor": 0.000000,"number_mean_queue": 0.000000,"lambda_in": 0.000000},"batch": {"service_demand": 0.000000,"response_time": 0.000000,"utilization_factor": 0.000000,"number_mean_queue": 0.000000,"lambda_in": 0.000000},"N_new": 0.070659,"N_new_stable": 0.070633},"node_type": "local"},{"id": 109,"sim_time": 3701286.466642,"stable": 1,"cost": 92.300000,"upper_node": 848,"sim_proc": 1,"sim_proc_multi": 1000,"preemption": 0,"scheduler": "FIFO","time_slice": 0.200000,"type": "node","parameters": {"telemetry": {"service_demand": 0.200147,"response_time": 0.214313,"utilization_factor": 0.066044,"number_mean_queue": 0.070719,"lambda_in": 0.329979},"transition": {"service_demand": 0.000000,"response_time": 0.000000,"utilization_factor": 0.000000,"number_mean_queue": 0.000000,"lambda_in": 0.000000},"command": {"service_demand": 0.000000,"response_time": 0.000000,"utilization_factor": 0.000000,"number_mean_queue": 0.000000,"lambda_in": 0.000000},"batch": {"service_demand": 0.000000,"response_time": 0.000000,"utilization_factor": 0.000000,"number_mean_queue": 0.000000,"lambda_in": 0.000000},"N_new": 0.070745,"N_new_stable": 0.070719},"node_type": "local"},{"id": 110,"sim_time": 3701289.193265,"stable": 1,"cost": 92.300000,"upper_node": 848,"sim_proc": 1,"sim_proc_multi": 1000,"preemption": 0,"scheduler": "FIFO","time_slice": 0.200000,"type": "node","parameters": {"telemetry": {"service_demand": 0.200117,"response_time": 0.214243,"utilization_factor": 0.066121,"number_mean_queue": 0.070788,"lambda_in": 0.330412},"transition": {"service_demand": 0.000000,"response_time": 0.000000,"utilization_factor": 0.000000,"number_mean_queue": 0.000000,"lambda_in": 0.000000},"command": {"service_demand": 0.000000,"response_time": 0.000000,"utilization_factor": 0.000000,"number_mean_queue": 0.000000,"lambda_in": 0.000000},"batch": {"service_demand": 0.000000,"response_time": 0.000000,"utilization_factor": 0.000000,"number_mean_queue": 0.000000,"lambda_in": 0.000000},"N_new": 0.070813,"N_new_stable": 0.070788},"node_type": "local"},{"id": 848,"upper_node": 7,"delay": 0.010000,"cost": 0.300000,"type": "wan"},{"id": 942,"sim_time": 3701281.091468,"stable": 1,"cost": 2.300000,"upper_node": 101,"type": "lan","lan_in": {"sim_proc": 1,"sim_proc_multi": 1000,"preemption": 0,"scheduler": "FIFO","time_slice": 0.000000,"telemetry": {"service_demand": 0.000000,"response_time": 0.000000,"utilization_factor": 0.000000,"number_mean_queue": 0.000000,"lambda_in": 0.000000},"transition": {"service_demand": 0.000000,"response_time": 0.000000,"utilization_factor": 0.000000,"number_mean_queue": 0.000000,"lambda_in": 0.000000},"command": {"service_demand": 0.000000,"response_time": 0.000000,"utilization_factor": 0.000000,"number_mean_queue": 0.000000,"lambda_in": 0.000000},"batch": {"service_demand": 0.000000,"response_time": 0.000000,"utilization_factor": 0.000000,"number_mean_queue": 0.000000,"lambda_in": 0.000000},"N_new": 0.000000,"N_new_stable": 0.000000},"lan_out": {"sim_proc": 1,"sim_proc_multi": 1000,"preemption": 0,"scheduler": "FIFO","time_slice": 0.000000,"telemetry": {"service_demand": 0.000000,"response_time": 0.000000,"utilization_factor": 0.000000,"number_mean_queue": 0.000000,"lambda_in": 0.329969},"transition": {"service_demand": 0.000000,"response_time": 0.000000,"utilization_factor": 0.000000,"number_mean_queue": 0.000000,"lambda_in": 0.000000},"command": {"service_demand": 0.000000,"response_time": 0.000000,"utilization_factor": 0.000000,"number_mean_queue": 0.000000,"lambda_in": 0.000000},"batch": {"service_demand": 0.000000,"response_time": 0.000000,"utilization_factor": 0.000000,"number_mean_queue": 0.000000,"lambda_in": 0.000000},"N_new": 0.000000,"N_new_stable": 0.000000},"node_type": ""},{"id": 943,"sim_time": 3701289.112342,"stable": 1,"cost": 2.300000,"upper_node": 102,"type": "lan","lan_in": {"sim_proc": 1,"sim_proc_multi": 1000,"preemption": 0,"scheduler": "FIFO","time_slice": 0.000000,"telemetry": {"service_demand": 0.000000,"response_time": 0.000000,"utilization_factor": 0.000000,"number_mean_queue": 0.000000,"lambda_in": 0.000000},"transition": {"service_demand": 0.000000,"response_time": 0.000000,"utilization_factor": 0.000000,"number_mean_queue": 0.000000,"lambda_in": 0.000000},"command": {"service_demand": 0.000000,"response_time": 0.000000,"utilization_factor": 0.000000,"number_mean_queue": 0.000000,"lambda_in": 0.000000},"batch": {"service_demand": 0.000000,"response_time": 0.000000,"utilization_factor": 0.000000,"number_mean_queue": 0.000000,"lambda_in": 0.000000},"N_new": 0.000000,"N_new_stable": 0.000000},"lan_out": {"sim_proc": 1,"sim_proc_multi": 1000,"preemption": 0,"scheduler": "FIFO","time_slice": 0.000000,"telemetry": {"service_demand": 0.000000,"response_time": 0.000000,"utilization_factor": 0.000000,"number_mean_queue": 0.000000,"lambda_in": 0.329731},"transition": {"service_demand": 0.000000,"response_time": 0.000000,"utilization_factor": 0.000000,"number_mean_queue": 0.000000,"lambda_in": 0.000000},"command": {"service_demand": 0.000000,"response_time": 0.000000,"utilization_factor": 0.000000,"number_mean_queue": 0.000000,"lambda_in": 0.000000},"batch": {"service_demand": 0.000000,"response_time": 0.000000,"utilization_factor": 0.000000,"number_mean_queue": 0.000000,"lambda_in": 0.000000},"N_new": 0.000000,"N_new_stable": 0.000000},"node_type": ""},{"id": 944,"sim_time": 3701287.588055,"stable": 1,"cost": 2.300000,"upper_node": 103,"type": "lan","lan_in": {"sim_proc": 1,"sim_proc_multi": 1000,"preemption": 0,"scheduler": "FIFO","time_slice": 0.000000,"telemetry": {"service_demand": 0.000000,"response_time": 0.000000,"utilization_factor": 0.000000,"number_mean_queue": 0.000000,"lambda_in": 0.000000},"transition": {"service_demand": 0.000000,"response_time": 0.000000,"utilization_factor": 0.000000,"number_mean_queue": 0.000000,"lambda_in": 0.000000},"command": {"service_demand": 0.000000,"response_time": 0.000000,"utilization_factor": 0.000000,"number_mean_queue": 0.000000,"lambda_in": 0.000000},"batch": {"service_demand": 0.000000,"response_time": 0.000000,"utilization_factor": 0.000000,"number_mean_queue": 0.000000,"lambda_in": 0.000000},"N_new": 0.000000,"N_new_stable": 0.000000},"lan_out": {"sim_proc": 1,"sim_proc_multi": 1000,"preemption": 0,"scheduler": "FIFO","time_slice": 0.000000,"telemetry": {"service_demand": 0.000000,"response_time": 0.000000,"utilization_factor": 0.000000,"number_mean_queue": 0.000000,"lambda_in": 0.330166},"transition": {"service_demand": 0.000000,"response_time": 0.000000,"utilization_factor": 0.000000,"number_mean_queue": 0.000000,"lambda_in": 0.000000},"command": {"service_demand": 0.000000,"response_time": 0.000000,"utilization_factor": 0.000000,"number_mean_queue": 0.000000,"lambda_in": 0.000000},"batch": {"service_demand": 0.000000,"response_time": 0.000000,"utilization_factor": 0.000000,"number_mean_queue": 0.000000,"lambda_in": 0.000000},"N_new": 0.000000,"N_new_stable": 0.000000},"node_type": ""},{"id": 945,"sim_time": 3701287.506085,"stable": 1,"cost": 2.300000,"upper_node": 104,"type": "lan","lan_in": {"sim_proc": 1,"sim_proc_multi": 1000,"preemption": 0,"scheduler": "FIFO","time_slice": 0.000000,"telemetry": {"service_demand": 0.000000,"response_time": 0.000000,"utilization_factor": 0.000000,"number_mean_queue": 0.000000,"lambda_in": 0.000000},"transition": {"service_demand": 0.000000,"response_time": 0.000000,"utilization_factor": 0.000000,"number_mean_queue": 0.000000,"lambda_in": 0.000000},"command": {"service_demand": 0.000000,"response_time": 0.000000,"utilization_factor": 0.000000,"number_mean_queue": 0.000000,"lambda_in": 0.000000},"batch": {"service_demand": 0.000000,"response_time": 0.000000,"utilization_factor": 0.000000,"number_mean_queue": 0.000000,"lambda_in": 0.000000},"N_new": 0.000000,"N_new_stable": 0.000000},"lan_out": {"sim_proc": 1,"sim_proc_multi": 1000,"preemption": 0,"scheduler": "FIFO","time_slice": 0.000000,"telemetry": {"service_demand": 0.000000,"response_time": 0.000000,"utilization_factor": 0.000000,"number_mean_queue": 0.000000,"lambda_in": 0.330607},"transition": {"service_demand": 0.000000,"response_time": 0.000000,"utilization_factor": 0.000000,"number_mean_queue": 0.000000,"lambda_in": 0.000000},"command": {"service_demand": 0.000000,"response_time": 0.000000,"utilization_factor": 0.000000,"number_mean_queue": 0.000000,"lambda_in": 0.000000},"batch": {"service_demand": 0.000000,"response_time": 0.000000,"utilization_factor": 0.000000,"number_mean_queue": 0.000000,"lambda_in": 0.000000},"N_new": 0.000000,"N_new_stable": 0.000000},"node_type": ""},{"id": 946,"sim_time": 3701285.654145,"stable": 1,"cost": 2.300000,"upper_node": 105,"type": "lan","lan_in": {"sim_proc": 1,"sim_proc_multi": 1000,"preemption": 0,"scheduler": "FIFO","time_slice": 0.000000,"telemetry": {"service_demand": 0.000000,"response_time": 0.000000,"utilization_factor": 0.000000,"number_mean_queue": 0.000000,"lambda_in": 0.000000},"transition": {"service_demand": 0.000000,"response_time": 0.000000,"utilization_factor": 0.000000,"number_mean_queue": 0.000000,"lambda_in": 0.000000},"command": {"service_demand": 0.000000,"response_time": 0.000000,"utilization_factor": 0.000000,"number_mean_queue": 0.000000,"lambda_in": 0.000000},"batch": {"service_demand": 0.000000,"response_time": 0.000000,"utilization_factor": 0.000000,"number_mean_queue": 0.000000,"lambda_in": 0.000000},"N_new": 0.000000,"N_new_stable": 0.000000},"lan_out": {"sim_proc": 1,"sim_proc_multi": 1000,"preemption": 0,"scheduler": "FIFO","time_slice": 0.000000,"telemetry": {"service_demand": 0.000000,"response_time": 0.000000,"utilization_factor": 0.000000,"number_mean_queue": 0.000000,"lambda_in": 0.330554},"transition": {"service_demand": 0.000000,"response_time": 0.000000,"utilization_factor": 0.000000,"number_mean_queue": 0.000000,"lambda_in": 0.000000},"command": {"service_demand": 0.000000,"response_time": 0.000000,"utilization_factor": 0.000000,"number_mean_queue": 0.000000,"lambda_in": 0.000000},"batch": {"service_demand": 0.000000,"response_time": 0.000000,"utilization_factor": 0.000000,"number_mean_queue": 0.000000,"lambda_in": 0.000000},"N_new": 0.000000,"N_new_stable": 0.000000},"node_type": ""},{"id": 947,"sim_time": 3701287.295915,"stable": 1,"cost": 2.300000,"upper_node": 106,"type": "lan","lan_in": {"sim_proc": 1,"sim_proc_multi": 1000,"preemption": 0,"scheduler": "FIFO","time_slice": 0.000000,"telemetry": {"service_demand": 0.000000,"response_time": 0.000000,"utilization_factor": 0.000000,"number_mean_queue": 0.000000,"lambda_in": 0.000000},"transition": {"service_demand": 0.000000,"response_time": 0.000000,"utilization_factor": 0.000000,"number_mean_queue": 0.000000,"lambda_in": 0.000000},"command": {"service_demand": 0.000000,"response_time": 0.000000,"utilization_factor": 0.000000,"number_mean_queue": 0.000000,"lambda_in": 0.000000},"batch": {"service_demand": 0.000000,"response_time": 0.000000,"utilization_factor": 0.000000,"number_mean_queue": 0.000000,"lambda_in": 0.000000},"N_new": 0.000000,"N_new_stable": 0.000000},"lan_out": {"sim_proc": 1,"sim_proc_multi": 1000,"preemption": 0,"scheduler": "FIFO","time_slice": 0.000000,"telemetry": {"service_demand": 0.000000,"response_time": 0.000000,"utilization_factor": 0.000000,"number_mean_queue": 0.000000,"lambda_in": 0.330010},"transition": {"service_demand": 0.000000,"response_time": 0.000000,"utilization_factor": 0.000000,"number_mean_queue": 0.000000,"lambda_in": 0.000000},"command": {"service_demand": 0.000000,"response_time": 0.000000,"utilization_factor": 0.000000,"number_mean_queue": 0.000000,"lambda_in": 0.000000},"batch": {"service_demand": 0.000000,"response_time": 0.000000,"utilization_factor": 0.000000,"number_mean_queue": 0.000000,"lambda_in": 0.000000},"N_new": 0.000000,"N_new_stable": 0.000000},"node_type": ""},{"id": 948,"sim_time": 3701287.993911,"stable": 1,"cost": 2.300000,"upper_node": 107,"type": "lan","lan_in": {"sim_proc": 1,"sim_proc_multi": 1000,"preemption": 0,"scheduler": "FIFO","time_slice": 0.000000,"telemetry": {"service_demand": 0.000000,"response_time": 0.000000,"utilization_factor": 0.000000,"number_mean_queue": 0.000000,"lambda_in": 0.000000},"transition": {"service_demand": 0.000000,"response_time": 0.000000,"utilization_factor": 0.000000,"number_mean_queue": 0.000000,"lambda_in": 0.000000},"command": {"service_demand": 0.000000,"response_time": 0.000000,"utilization_factor": 0.000000,"number_mean_queue": 0.000000,"lambda_in": 0.000000},"batch": {"service_demand": 0.000000,"response_time": 0.000000,"utilization_factor": 0.000000,"number_mean_queue": 0.000000,"lambda_in": 0.000000},"N_new": 0.000000,"N_new_stable": 0.000000},"lan_out": {"sim_proc": 1,"sim_proc_multi": 1000,"preemption": 0,"scheduler": "FIFO","time_slice": 0.000000,"telemetry": {"service_demand": 0.000000,"response_time": 0.000000,"utilization_factor": 0.000000,"number_mean_queue": 0.000000,"lambda_in": 0.329967},"transition": {"service_demand": 0.000000,"response_time": 0.000000,"utilization_factor": 0.000000,"number_mean_queue": 0.000000,"lambda_in": 0.000000},"command": {"service_demand": 0.000000,"response_time": 0.000000,"utilization_factor": 0.000000,"number_mean_queue": 0.000000,"lambda_in": 0.000000},"batch": {"service_demand": 0.000000,"response_time": 0.000000,"utilization_factor": 0.000000,"number_mean_queue": 0.000000,"lambda_in": 0.000000},"N_new": 0.000000,"N_new_stable": 0.000000},"node_type": ""},{"id": 949,"sim_time": 3701289.844737,"stable": 1,"cost": 2.300000,"upper_node": 108,"type": "lan","lan_in": {"sim_proc": 1,"sim_proc_multi": 1000,"preemption": 0,"scheduler": "FIFO","time_slice": 0.000000,"telemetry": {"service_demand": 0.000000,"response_time": 0.000000,"utilization_factor": 0.000000,"number_mean_queue": 0.000000,"lambda_in": 0.000000},"transition": {"service_demand": 0.000000,"response_time": 0.000000,"utilization_factor": 0.000000,"number_mean_queue": 0.000000,"lambda_in": 0.000000},"command": {"service_demand": 0.000000,"response_time": 0.000000,"utilization_factor": 0.000000,"number_mean_queue": 0.000000,"lambda_in": 0.000000},"batch": {"service_demand": 0.000000,"response_time": 0.000000,"utilization_factor": 0.000000,"number_mean_queue": 0.000000,"lambda_in": 0.000000},"N_new": 0.000000,"N_new_stable": 0.000000},"lan_out": {"sim_proc": 1,"sim_proc_multi": 1000,"preemption": 0,"scheduler": "FIFO","time_slice": 0.000000,"telemetry": {"service_demand": 0.000000,"response_time": 0.000000,"utilization_factor": 0.000000,"number_mean_queue": 0.000000,"lambda_in": 0.329903},"transition": {"service_demand": 0.000000,"response_time": 0.000000,"utilization_factor": 0.000000,"number_mean_queue": 0.000000,"lambda_in": 0.000000},"command": {"service_demand": 0.000000,"response_time": 0.000000,"utilization_factor": 0.000000,"number_mean_queue": 0.000000,"lambda_in": 0.000000},"batch": {"service_demand": 0.000000,"response_time": 0.000000,"utilization_factor": 0.000000,"number_mean_queue": 0.000000,"lambda_in": 0.000000},"N_new": 0.000000,"N_new_stable": 0.000000},"node_type": ""},{"id": 950,"sim_time": 3701286.148382,"stable": 1,"cost": 2.300000,"upper_node": 109,"type": "lan","lan_in": {"sim_proc": 1,"sim_proc_multi": 1000,"preemption": 0,"scheduler": "FIFO","time_slice": 0.000000,"telemetry": {"service_demand": 0.000000,"response_time": 0.000000,"utilization_factor": 0.000000,"number_mean_queue": 0.000000,"lambda_in": 0.000000},"transition": {"service_demand": 0.000000,"response_time": 0.000000,"utilization_factor": 0.000000,"number_mean_queue": 0.000000,"lambda_in": 0.000000},"command": {"service_demand": 0.000000,"response_time": 0.000000,"utilization_factor": 0.000000,"number_mean_queue": 0.000000,"lambda_in": 0.000000},"batch": {"service_demand": 0.000000,"response_time": 0.000000,"utilization_factor": 0.000000,"number_mean_queue": 0.000000,"lambda_in": 0.000000},"N_new": 0.000000,"N_new_stable": 0.000000},"lan_out": {"sim_proc": 1,"sim_proc_multi": 1000,"preemption": 0,"scheduler": "FIFO","time_slice": 0.000000,"telemetry": {"service_demand": 0.000000,"response_time": 0.000000,"utilization_factor": 0.000000,"number_mean_queue": 0.000000,"lambda_in": 0.329982},"transition": {"service_demand": 0.000000,"response_time": 0.000000,"utilization_factor": 0.000000,"number_mean_queue": 0.000000,"lambda_in": 0.000000},"command": {"service_demand": 0.000000,"response_time": 0.000000,"utilization_factor": 0.000000,"number_mean_queue": 0.000000,"lambda_in": 0.000000},"batch": {"service_demand": 0.000000,"response_time": 0.000000,"utilization_factor": 0.000000,"number_mean_queue": 0.000000,"lambda_in": 0.000000},"N_new": 0.000000,"N_new_stable": 0.000000},"node_type": ""},{"id": 951,"sim_time": 3701288.905966,"stable": 1,"cost": 2.300000,"upper_node": 110,"type": "lan","lan_in": {"sim_proc": 1,"sim_proc_multi": 1000,"preemption": 0,"scheduler": "FIFO","time_slice": 0.000000,"telemetry": {"service_demand": 0.000000,"response_time": 0.000000,"utilization_factor": 0.000000,"number_mean_queue": 0.000000,"lambda_in": 0.000000},"transition": {"service_demand": 0.000000,"response_time": 0.000000,"utilization_factor": 0.000000,"number_mean_queue": 0.000000,"lambda_in": 0.000000},"command": {"service_demand": 0.000000,"response_time": 0.000000,"utilization_factor": 0.000000,"number_mean_queue": 0.000000,"lambda_in": 0.000000},"batch": {"service_demand": 0.000000,"response_time": 0.000000,"utilization_factor": 0.000000,"number_mean_queue": 0.000000,"lambda_in": 0.000000},"N_new": 0.000000,"N_new_stable": 0.000000},"lan_out": {"sim_proc": 1,"sim_proc_multi": 1000,"preemption": 0,"scheduler": "FIFO","time_slice": 0.000000,"telemetry": {"service_demand": 0.000000,"response_time": 0.000000,"utilization_factor": 0.000000,"number_mean_queue": 0.000000,"lambda_in": 0.330407},"transition": {"service_demand": 0.000000,"response_time": 0.000000,"utilization_factor": 0.000000,"number_mean_queue": 0.000000,"lambda_in": 0.000000},"command": {"service_demand": 0.000000,"response_time": 0.000000,"utilization_factor": 0.000000,"number_mean_queue": 0.000000,"lambda_in": 0.000000},"batch": {"service_demand": 0.000000,"response_time": 0.000000,"utilization_factor": 0.000000,"number_mean_queue": 0.000000,"lambda_in": 0.000000},"N_new": 0.000000,"N_new_stable": 0.000000},"node_type": ""}]